enricher/84.json
enricher/85.json
enricher/86.json
enricher/87.json
enricher/88.json
enricher/89.json
enricher/90.json
enricher/91.json
enricher/92.json
enricher/__init__.py
enricher/enricher.py
kg_enricher-0.1.9.dist-info/LICENSE
kg_enricher-0.1.9.dist-info/METADATA
kg_enricher-0.1.9.dist-info/WHEEL
kg_enricher-0.1.9.dist-info/top_level.txt
kg_enricher-0.1.9.dist-info/RECORD
