Metadata-Version: 2.1
Name: kg-enricher
Version: 0.1.9
Summary: A Python library for enriching strings, entities and KGs using Wikibase knowledge graphs. It's adapted for people, organizations and German geographic entities, both modern and historical.
Home-page: https://github.com/UB-Mannheim/kg-enricher
Author: Renat Shigapov
License: MIT
Classifier: Programming Language :: Python :: 3
Classifier: License :: OSI Approved :: MIT License
Classifier: Operating System :: OS Independent
Requires-Python: >=3.7
License-File: LICENSE
Requires-Dist: geopandas
Requires-Dist: shapely
Requires-Dist: requests
Requires-Dist: appengine-python-standard
